hello_world/__init__.py
hello_world/hello_world.py
floydpink.jsii_native_python-0.1.0.dist-info/LICENSE
floydpink.jsii_native_python-0.1.0.dist-info/METADATA
floydpink.jsii_native_python-0.1.0.dist-info/WHEEL
floydpink.jsii_native_python-0.1.0.dist-info/top_level.txt
floydpink.jsii_native_python-0.1.0.dist-info/RECORD
