Metadata-Version: 2.1
Name: floydpink.jsii-native-python
Version: 0.1.0
Summary: A simple Python library to benchmark against a jsii module with similar, simple logic.
Home-page: https://github.com/floydpink/jsii-native-python
Author: Hari Pachuveetil
Author-email: imbleedingme@googlemail.com
License: MIT
Download-URL: https://pypi.org/project/jsii-native-python/
Keywords: jsii,python,java,dotnet,typescript,aws
Platform: UNKNOWN
